{"cameraMode":{"drawMode":0,"name":"Shaded","section":"Shading Mode"},"sceneLighting":true,"audioPlay":false,"sceneViewState":{"showFog":false,"showMaterialUpdate":false,"showSkybox":false,"showFlares":false,"showImageEffects":false,"showParticleSystems":false},"in2DMode":false,"pivot":{"x":-0.755859375,"y":1.0634765625,"z":-13.22613525390625},"rotation":{"x":-0.15871596336364747,"y":0.7023733258247376,"z":-0.16542711853981019,"w":-0.6738826036453247},"size":4.815800189971924,"orthographic":false}